<?xml version="1.0" encoding="UTF-8"?><database>
    <element db_object_id="fc756d51475f21103fa44aff336d435a" label="Pass Mark Library" max_length="40" name="x_431105_cand_ass_pass_mark_library" type="collection">
        <element label="Competencies" max_length="1024" name="competencies" reference="x_431105_cand_ass_selection_criteria_library" reference_qual="active=true^EQ" reference_qual_condition="active=true^EQ" type="glide_list"/>
        <element choice="1" choice_field="minimum_value" choice_table="x_431105_cand_ass_pass_mark" label="Minimum value" max_length="40" name="minimum_value" type="integer">
            <choice/>
        </element>
        <element label="Name" max_length="40" name="name" type="string"/>
        <element attributes="edge_encryption_enabled=true" default="javascript:global.getNextObjNumberPadded();" label="Number" max_length="40" name="number" type="string"/>
    </element>
</database>
