<?xml version="1.0" encoding="UTF-8"?><record_update sys_domain="global" table="sys_ux_screen">
    <sys_ux_screen action="DELETE">
        <active>true</active>
        <app_config display_value="Candidate Assessment Config">3c8dccd2b048a5109cdf0d066aa3205e</app_config>
        <description/>
        <event_mappings/>
        <macroponent display_value="KPI Details">ed7ad8a1c313101001a6e0dd9740ddd1</macroponent>
        <macroponent_config>{
  "label" : "",
  "bare" : true,
  "scrollable" : "y",
  "headerLevel" : "1",
  "interceptNotifications" : false,
  "propagateNotifications" : false,
  "sysId" : "",
  "views" : "",
  "selectedTabIndex" : 0,
  "table" : "",
  "mode" : "",
  "listView" : ""
}</macroponent_config>
        <name>KPI Details default</name>
        <order>0</order>
        <parent_macroponent display_value="Agent Workspace App Shell">c276387cc331101080d6d3658940ddd2</parent_macroponent>
        <required_translations>[ ]</required_translations>
        <rollback_screen/>
        <screen_condition/>
        <screen_type display_value="KPI Details">348dccd25448a51040b31b418b18715e</screen_type>
        <sys_class_name>sys_ux_screen</sys_class_name>
        <sys_created_by>admin</sys_created_by>
        <sys_created_on>2022-12-30 12:50:46</sys_created_on>
        <sys_domain>global</sys_domain>
        <sys_domain_path>/</sys_domain_path>
        <sys_id>f88dccd21248a510127b111ad3646f5b</sys_id>
        <sys_mod_count>0</sys_mod_count>
        <sys_name>KPI Details default</sys_name>
        <sys_overrides/>
        <sys_package display_value="Candidate Assessment" source="x_431105_cand_ass">3aeff01497c02110a4deb9dfe153afb4</sys_package>
        <sys_policy/>
        <sys_scope display_value="Candidate Assessment">3aeff01497c02110a4deb9dfe153afb4</sys_scope>
        <sys_update_name>sys_ux_screen_f88dccd21248a510127b111ad3646f5b</sys_update_name>
        <sys_updated_by>admin</sys_updated_by>
        <sys_updated_on>2022-12-30 12:50:46</sys_updated_on>
    </sys_ux_screen>
    <sys_translated_text action="DELETE" query="documentkey=f88dccd21248a510127b111ad3646f5b"/>
<sys_update_version action="INSERT_OR_UPDATE">
        <action>DELETE</action>
        <application display_value="Talent NOW">3aeff01497c02110a4deb9dfe153afb4</application>
        <file_path/>
        <instance_id>ce1aa807db352d180b9d21c4059619e3</instance_id>
        <instance_name>dev168883</instance_name>
        <name>sys_ux_screen_f88dccd21248a510127b111ad3646f5b</name>
        <payload><![CDATA[<?xml version="1.0" encoding="UTF-8"?><record_update sys_domain="global" table="sys_ux_screen">
    <sys_ux_screen action="INSERT_OR_UPDATE">
        <active>true</active>
        <app_config display_value="Candidate Assessment Config">3c8dccd2b048a5109cdf0d066aa3205e</app_config>
        <description/>
        <event_mappings/>
        <macroponent display_value="KPI Details">ed7ad8a1c313101001a6e0dd9740ddd1</macroponent>
        <macroponent_config>{
  "label" : "",
  "bare" : true,
  "scrollable" : "y",
  "headerLevel" : "1",
  "interceptNotifications" : false,
  "propagateNotifications" : false,
  "sysId" : "",
  "views" : "",
  "selectedTabIndex" : 0,
  "table" : "",
  "mode" : "",
  "listView" : ""
}</macroponent_config>
        <name>KPI Details default</name>
        <order>0</order>
        <parent_macroponent display_value="Agent Workspace App Shell">c276387cc331101080d6d3658940ddd2</parent_macroponent>
        <required_translations>[ ]</required_translations>
        <rollback_screen/>
        <screen_condition/>
        <screen_type display_value="KPI Details">348dccd25448a51040b31b418b18715e</screen_type>
        <sys_class_name>sys_ux_screen</sys_class_name>
        <sys_created_by>admin</sys_created_by>
        <sys_created_on>2022-12-30 12:50:46</sys_created_on>
        <sys_domain>global</sys_domain>
        <sys_domain_path>/</sys_domain_path>
        <sys_id>f88dccd21248a510127b111ad3646f5b</sys_id>
        <sys_mod_count>0</sys_mod_count>
        <sys_name>KPI Details default</sys_name>
        <sys_overrides/>
        <sys_package display_value="Candidate Assessment" source="x_431105_cand_ass">3aeff01497c02110a4deb9dfe153afb4</sys_package>
        <sys_policy/>
        <sys_scope display_value="Candidate Assessment">3aeff01497c02110a4deb9dfe153afb4</sys_scope>
        <sys_update_name>sys_ux_screen_f88dccd21248a510127b111ad3646f5b</sys_update_name>
        <sys_updated_by>admin</sys_updated_by>
        <sys_updated_on>2022-12-30 12:50:46</sys_updated_on>
    </sys_ux_screen>
    <sys_translated_text action="delete_multiple" query="documentkey=f88dccd21248a510127b111ad3646f5b"/>
</record_update>]]></payload>
        <payload_hash>-231328700</payload_hash>
        <record_name>KPI Details default</record_name>
        <reverted_from/>
        <source>bde4534e470321103fa44aff336d4334</source>
        <source_table>sys_upgrade_history</source_table>
        <state>previous</state>
        <sys_created_by>admin</sys_created_by>
        <sys_created_on>2023-05-28 11:53:55</sys_created_on>
        <sys_id>95659f06474321103fa44aff336d439e</sys_id>
        <sys_mod_count>0</sys_mod_count>
        <sys_recorded_at>18862353a580000001</sys_recorded_at>
        <sys_updated_by>admin</sys_updated_by>
        <sys_updated_on>2023-05-28 11:53:55</sys_updated_on>
        <type>UX Screen</type>
        <update_guid>55659f06374321100688de97df7d679e</update_guid>
        <update_guid_history>55659f06374321100688de97df7d679e:-231328700</update_guid_history>
    </sys_update_version>
    <sys_metadata_delete action="INSERT_OR_UPDATE">
        <sys_audit_delete/>
        <sys_class_name>sys_metadata_delete</sys_class_name>
        <sys_created_by>nappoma</sys_created_by>
        <sys_created_on>2023-06-04 07:57:59</sys_created_on>
        <sys_db_object display_value="" name="sys_ux_screen">sys_ux_screen</sys_db_object>
        <sys_id>2d5379108b2649b3bb15a38832794101</sys_id>
        <sys_metadata>f88dccd21248a510127b111ad3646f5b</sys_metadata>
        <sys_mod_count>0</sys_mod_count>
        <sys_name>KPI Details default</sys_name>
        <sys_package display_value="Talent NOW" source="x_431105_cand_ass">3aeff01497c02110a4deb9dfe153afb4</sys_package>
        <sys_parent/>
        <sys_policy/>
        <sys_scope display_value="Talent NOW">3aeff01497c02110a4deb9dfe153afb4</sys_scope>
        <sys_scope_delete display_value="Talent NOW">102d0c1703d24bb18e1e1addf418fef1</sys_scope_delete>
        <sys_update_name>sys_ux_screen_f88dccd21248a510127b111ad3646f5b</sys_update_name>
        <sys_update_version display_value="sys_ux_screen_f88dccd21248a510127b111ad3646f5b">95659f06474321103fa44aff336d439e</sys_update_version>
        <sys_updated_by>nappoma</sys_updated_by>
        <sys_updated_on>2023-06-04 07:57:59</sys_updated_on>
    </sys_metadata_delete>
</record_update>
