<?xml version="1.0" encoding="UTF-8"?><record_update table="sys_ux_app_route">
    <sys_ux_app_route action="DELETE">
        <app_config display_value="Candidate Assessment Config">688983e0a1c0a110ef32212b07b8dc4c</app_config>
        <description/>
        <fields>uuid</fields>
        <icon/>
        <name>KPI Details</name>
        <optional_parameters>scoreDate,breakdowns,domain</optional_parameters>
        <order>0</order>
        <parent_macroponent display_value="Agent Workspace App Shell">c276387cc331101080d6d3658940ddd2</parent_macroponent>
        <parent_macroponent_composition_element_id/>
        <route_type>ac_kpi_details</route_type>
        <screen_type display_value="KPI Details">608983e09ec0a110d6fda535de768d4c</screen_type>
        <sys_class_name>sys_ux_app_route</sys_class_name>
        <sys_created_by>admin</sys_created_by>
        <sys_created_on>2022-12-25 16:02:46</sys_created_on>
        <sys_id>2c8983e000c0a110dbc255197e27cf4b</sys_id>
        <sys_mod_count>0</sys_mod_count>
        <sys_name>KPI Details</sys_name>
        <sys_package display_value="Candidate Assessment" source="x_431105_cand_ass">3aeff01497c02110a4deb9dfe153afb4</sys_package>
        <sys_policy/>
        <sys_scope display_value="Candidate Assessment">3aeff01497c02110a4deb9dfe153afb4</sys_scope>
        <sys_update_name>sys_ux_app_route_2c8983e000c0a110dbc255197e27cf4b</sys_update_name>
        <sys_updated_by>admin</sys_updated_by>
        <sys_updated_on>2022-12-25 16:02:46</sys_updated_on>
    </sys_ux_app_route>
    <sys_translated_text action="DELETE" query="documentkey=2c8983e000c0a110dbc255197e27cf4b"/>
<sys_update_version action="INSERT_OR_UPDATE">
        <action>DELETE</action>
        <application display_value="Talent NOW">3aeff01497c02110a4deb9dfe153afb4</application>
        <file_path/>
        <instance_id>3b0c683cdbbe5190b847ac44d4961962</instance_id>
        <instance_name>dev142367</instance_name>
        <name>sys_ux_app_route_2c8983e000c0a110dbc255197e27cf4b</name>
        <payload><![CDATA[<?xml version="1.0" encoding="UTF-8"?><record_update table="sys_ux_app_route">
    <sys_ux_app_route action="INSERT_OR_UPDATE">
        <app_config display_value="Candidate Assessment Config">688983e0a1c0a110ef32212b07b8dc4c</app_config>
        <description/>
        <fields>uuid</fields>
        <icon/>
        <name>KPI Details</name>
        <optional_parameters>scoreDate,breakdowns,domain</optional_parameters>
        <order>0</order>
        <parent_macroponent display_value="Agent Workspace App Shell">c276387cc331101080d6d3658940ddd2</parent_macroponent>
        <parent_macroponent_composition_element_id/>
        <route_type>ac_kpi_details</route_type>
        <screen_type display_value="KPI Details">608983e09ec0a110d6fda535de768d4c</screen_type>
        <sys_class_name>sys_ux_app_route</sys_class_name>
        <sys_created_by>admin</sys_created_by>
        <sys_created_on>2022-12-25 16:02:46</sys_created_on>
        <sys_id>2c8983e000c0a110dbc255197e27cf4b</sys_id>
        <sys_mod_count>0</sys_mod_count>
        <sys_name>KPI Details</sys_name>
        <sys_package display_value="Candidate Assessment" source="x_431105_cand_ass">3aeff01497c02110a4deb9dfe153afb4</sys_package>
        <sys_policy/>
        <sys_scope display_value="Candidate Assessment">3aeff01497c02110a4deb9dfe153afb4</sys_scope>
        <sys_update_name>sys_ux_app_route_2c8983e000c0a110dbc255197e27cf4b</sys_update_name>
        <sys_updated_by>admin</sys_updated_by>
        <sys_updated_on>2022-12-25 16:02:46</sys_updated_on>
    </sys_ux_app_route>
    <sys_translated_text action="delete_multiple" query="documentkey=2c8983e000c0a110dbc255197e27cf4b"/>
</record_update>]]></payload>
        <payload_hash>-1631687515</payload_hash>
        <record_name>KPI Details</record_name>
        <reverted_from/>
        <source>507826e247f62110691e7258946d4389</source>
        <source_table>sys_upgrade_history</source_table>
        <state>previous</state>
        <sys_created_by>admin</sys_created_by>
        <sys_created_on>2023-05-17 11:39:40</sys_created_on>
        <sys_id>89a8e26647f62110691e7258946d43df</sys_id>
        <sys_mod_count>0</sys_mod_count>
        <sys_recorded_at>18829823b040000001</sys_recorded_at>
        <sys_updated_by>admin</sys_updated_by>
        <sys_updated_on>2023-05-17 11:39:40</sys_updated_on>
        <type>UX App Route</type>
        <update_guid>49a8e266a3f621109ab952ca55fba3df</update_guid>
        <update_guid_history>49a8e266a3f621109ab952ca55fba3df:-1631687515</update_guid_history>
    </sys_update_version>
    <sys_metadata_delete action="INSERT_OR_UPDATE">
        <sys_audit_delete/>
        <sys_class_name>sys_metadata_delete</sys_class_name>
        <sys_created_by>admin</sys_created_by>
        <sys_created_on>2023-05-17 13:48:41</sys_created_on>
        <sys_db_object display_value="" name="sys_ux_app_route">sys_ux_app_route</sys_db_object>
        <sys_id>105d22ee79634b409e9ce4ca387ec400</sys_id>
        <sys_metadata>2c8983e000c0a110dbc255197e27cf4b</sys_metadata>
        <sys_mod_count>0</sys_mod_count>
        <sys_name>KPI Details</sys_name>
        <sys_package display_value="Talent NOW" source="x_431105_cand_ass">3aeff01497c02110a4deb9dfe153afb4</sys_package>
        <sys_parent/>
        <sys_policy/>
        <sys_scope display_value="Talent NOW">3aeff01497c02110a4deb9dfe153afb4</sys_scope>
        <sys_scope_delete/>
        <sys_update_name>sys_ux_app_route_2c8983e000c0a110dbc255197e27cf4b</sys_update_name>
        <sys_update_version display_value="sys_ux_app_route_2c8983e000c0a110dbc255197e27cf4b">89a8e26647f62110691e7258946d43df</sys_update_version>
        <sys_updated_by>admin</sys_updated_by>
        <sys_updated_on>2023-05-17 13:48:41</sys_updated_on>
    </sys_metadata_delete>
</record_update>
